TableGen/TableGenUtils.py
TableGen/TempFileListener.py
TableGen/__init__.py
tablegen-1.1.0.dist-info/LICENSE
tablegen-1.1.0.dist-info/METADATA
tablegen-1.1.0.dist-info/WHEEL
tablegen-1.1.0.dist-info/top_level.txt
tablegen-1.1.0.dist-info/RECORD
