Metadata-Version: 2.1
Name: tablegen
Version: 1.1.0
Summary: Quickly convert a list of dictionaries to human readable tables
Home-page: https://github.com/yotamabt/TableGen
Author: Yotam Abt
Author-email: yotamabt@gmail.com
License: UNKNOWN
Platform: UNKNOWN
Classifier: Programming Language :: Python :: 3
Classifier: License :: OSI Approved :: MIT License
Classifier: Operating System :: OS Independent
Requires-Python: >=3.6
